ranger_tmux/__init__.py
ranger_tmux/__main__.py
ranger_tmux/cwd_sync.py
ranger_tmux/cwd_track.py
ranger_tmux/drop.py
ranger_tmux/dropdown.py
ranger_tmux/open_in_window.py
ranger_tmux/plugin.py
ranger_tmux/set_window_name.py
ranger_tmux/splits.py
ranger_tmux/util.py
ranger_tmux-1.0.8.dist-info/entry_points.txt
ranger_tmux-1.0.8.dist-info/LICENSE
ranger_tmux-1.0.8.dist-info/WHEEL
ranger_tmux-1.0.8.dist-info/METADATA
ranger_tmux-1.0.8.dist-info/RECORD
