Metadata-Version: 2.1
Name: ranger-tmux
Version: 1.0.8
Summary: Tmux integration for ranger
Home-page: https://github.com/joouha/ranger_tmux
License: MIT
Author: Josiah Outram Halstead
Author-email: josiah@halstead.email
Requires-Python: >=2.7, !=3.0.*, !=3.1.*, !=3.2.*, !=3.3.*, !=3.4.*, !=3.5.*
Classifier: Environment :: Plugins
Classifier: License :: OSI Approved :: MIT License
Classifier: Programming Language :: Python :: 2
Classifier: Programming Language :: Python :: 2.7
Classifier: Programming Language :: Python :: 3
Classifier: Programming Language :: Python :: 3.6
Classifier: Programming Language :: Python :: 3.7
Classifier: Programming Language :: Python :: 3.8
Classifier: Programming Language :: Python :: 3.9
Classifier: Programming Language :: Python :: 3.10
Classifier: Programming Language :: Python :: 3.11
Requires-Dist: importlib-metadata (>=2.1.2); python_version >= "2.7" and python_version < "3.8"
Requires-Dist: importlib-resources (>=3.3.1); python_version >= "2.7" and python_version < "3.9"
Requires-Dist: pathlib2 (>=2.3.6,<3.0.0); python_full_version > "2.7.0" and python_version < "3"
Requires-Dist: psutil (>=5.8.0,<6.0.0)
Requires-Dist: ranger-fm (>=1.9.3,<2.0.0)
